PyRTF/Constants.py
PyRTF/Elements.py
PyRTF/PropertySets.py
PyRTF/Renderer.py
PyRTF/Styles.py
PyRTF/__init__.py
PyRTF/_version.py
PyRTF/ertf.py
PyRTF/utils.py
PyRTF/document/__init__.py
PyRTF/document/base.py
PyRTF/document/character.py
PyRTF/document/paragraph.py
PyRTF/document/section.py
PyRTF/object/__init__.py
PyRTF/object/picture.py
PyRTF/parser/__init__.py
PyRTF/parser/base.py
PyRTF/parser/grammar.py
PyRTF/writer/__init__.py
PyRTF3-0.47.4.dist-info/DESCRIPTION.rst
PyRTF3-0.47.4.dist-info/METADATA
PyRTF3-0.47.4.dist-info/RECORD
PyRTF3-0.47.4.dist-info/WHEEL
PyRTF3-0.47.4.dist-info/metadata.json
PyRTF3-0.47.4.dist-info/top_level.txt
tests/__init__.py
tests/test_all.py
tests/test_doctests.py
tests/document/__init__.py
tests/document/test_characters.py
tests/document/test_document.py
tests/document/test_headerfooter.py
tests/document/test_paragraphs.py
tests/document/test_sections.py
tests/document/test_tables.py
tests/header/__init__.py
tests/objects/__init__.py
tests/objects/test_pictures.py
