Metadata-Version: 2.0
Name: PyRTF3
Version: 0.47.4
Summary: PyRTF - Rich Text Format Document Generation
Home-page: https://github.com/xoviat/pyrtf
Author: Mars Galactic
Author-email: xoviat@noreply.users.github.com
License: http://www.gnu.org/licenses/gpl.html
Keywords: RTF,Rich Text,Rich Text Format,documentation,reports
Platform: Any
Classifier: Development Status :: 4 - Beta
Classifier: Topic :: Text Editors :: Text Processing
Classifier: Topic :: Software Development :: Libraries :: Python Modules
Classifier: Intended Audience :: Developers
Classifier: Programming Language :: Python
Classifier: License :: OSI Approved :: GNU General Public License (GPL)
Requires-Dist: PyParsing
